bill_generator/__init__.py
bill_generator/__main__.py
bill_generator/main.py
bill_generator_cu_homework-0.1.0.dist-info/METADATA
bill_generator_cu_homework-0.1.0.dist-info/WHEEL
bill_generator_cu_homework-0.1.0.dist-info/top_level.txt
bill_generator_cu_homework-0.1.0.dist-info/RECORD
