Metadata-Version: 2.1
Name: bill-generator-cu-homework
Version: 0.1.0
Summary: Генератор чеков
Author-email: Matvey Perminov <mectu@mail.ru>
License: MIT
Requires-Python: >=3.12
